cg_flake8_reporter/__init__.py
cg_flake8_reporter/plugin.py
cg_flake8_reporter-2024.2.26.1340.dist-info/METADATA
cg_flake8_reporter-2024.2.26.1340.dist-info/WHEEL
cg_flake8_reporter-2024.2.26.1340.dist-info/entry_points.txt
cg_flake8_reporter-2024.2.26.1340.dist-info/RECORD
